hesperos/__init__.py
hesperos/_manual_widget.py
hesperos/_oneshot_widget.py
hesperos/napari.yaml
hesperos/annotation/__init__.py
hesperos/annotation/feta.py
hesperos/annotation/fetus.py
hesperos/annotation/larva.py
hesperos/annotation/mouse_embryon.py
hesperos/annotation/oneshot.py
hesperos/annotation/shoulder.py
hesperos/annotation/shoulder_bone_border.py
hesperos/annotation/shoulder_bones.py
hesperos/annotation/shoulder_deltoid.py
hesperos/annotation/structuresubpanel.py
hesperos/layout/__init__.py
hesperos/layout/gui_elements.py
hesperos/layout/napari_elements.py
hesperos/one_shot_learning/__init__.py
hesperos/one_shot_learning/classifier.py
hesperos/one_shot_learning/features2d.py
hesperos/one_shot_learning/features3d.py
hesperos/one_shot_learning/kernel.py
hesperos/one_shot_learning/utilities.py
hesperos/resources/__init__.py
hesperos/resources/_icons.py
hesperos/resources/group_box_stylesheet.qss
hesperos/resources/icons/__init__.py
hesperos/resources/icons/back.svg
hesperos/resources/icons/backup.svg
hesperos/resources/icons/chevron_down.svg
hesperos/resources/icons/chevron_left.svg
hesperos/resources/icons/chevron_right.svg
hesperos/resources/icons/chevron_up.svg
hesperos/resources/icons/export.svg
hesperos/resources/icons/import.svg
hesperos/resources/icons/lock.svg
hesperos/resources/icons/map.svg
hesperos/resources/icons/minus.svg
hesperos/resources/icons/minus2.svg
hesperos/resources/icons/next.svg
hesperos/resources/icons/plus.svg
hesperos/resources/icons/reset.svg
hesperos/resources/icons/save.svg
hesperos/resources/icons/undo.svg
hesperos/resources/icons/unlock.svg
hesperos/resources/icons/zoom.svg
hesperos-0.2.1.dist-info/LICENSE
hesperos-0.2.1.dist-info/METADATA
hesperos-0.2.1.dist-info/WHEEL
hesperos-0.2.1.dist-info/entry_points.txt
hesperos-0.2.1.dist-info/top_level.txt
hesperos-0.2.1.dist-info/RECORD
