Metadata-Version: 2.1
Name: hesperos
Version: 0.2.1
Summary: A plugin to manually or semi-automatically segment medical data and correct previous segmentation data.
Home-page: https://github.com/chgodard/hesperos
Author: Charlotte Godard
Author-email: charlotte.godard@pasteur.fr
License: BSD-3-Clause
Project-URL: Documentation, https://github.com/chgodard/hesperos/blob/main/README.md
Project-URL: Source Code, https://github.com/chgodard/hesperos
Classifier: Development Status :: 2 - Pre-Alpha
Classifier: Intended Audience :: Developers
Classifier: Framework :: napari
Classifier: Programming Language :: Python
Classifier: Programming Language :: Python :: 3
Classifier: Programming Language :: Python :: 3.8
Classifier: Programming Language :: Python :: 3.9
Classifier: Programming Language :: Python :: 3.10
Classifier: Operating System :: MacOS :: MacOS X
Classifier: Operating System :: Microsoft :: Windows
Classifier: License :: OSI Approved :: BSD License
Requires-Python: >=3.8
License-File: LICENSE
Requires-Dist: numpy
Requires-Dist: qtpy
Requires-Dist: tifffile
Requires-Dist: scikit-image
Requires-Dist: scikit-learn
Requires-Dist: SimpleITK
Requires-Dist: pandas
Requires-Dist: napari (<0.4.15)
Requires-Dist: napari-plugin-engine
Requires-Dist: imageio-ffmpeg
Provides-Extra: testing
Requires-Dist: tox ; extra == 'testing'
Requires-Dist: pytest ; extra == 'testing'
Requires-Dist: pytest-cov ; extra == 'testing'
Requires-Dist: pytest-qt ; extra == 'testing'
Requires-Dist: napari ; extra == 'testing'
Requires-Dist: pyqt5 ; extra == 'testing'
